gradle.properties
hexdoc_mediaworks/__gradle_version__.py
hexdoc_mediaworks/__init__.py
hexdoc_mediaworks/__version__.py
hexdoc_mediaworks/_hooks.py
hexdoc_mediaworks/py.typed
hexdoc_mediaworks/_export/.gitignore
hexdoc_mediaworks/_export/__init__.py
hexdoc_mediaworks/_export/generated/__init__.py
hexdoc_mediaworks/_export/generated/mediaworks.hexdoc.json
hexdoc_mediaworks/_export/generated/mediaworks.patterns.hexdoc.json
hexdoc_mediaworks/_export/generated/assets/hexcasting/lang/en_us.flatten.json5
hexdoc_mediaworks/_export/generated/assets/mediaworks/lang/en_us.json
hexdoc_mediaworks/_export/generated/assets/mediaworks/lang/zh_cn.json
hexdoc_mediaworks/_export/generated/assets/mediaworks/models/item/magic_cloak.json
hexdoc_mediaworks/_export/generated/assets/mediaworks/textures/item/magic_cloak.png
hexdoc_mediaworks/_export/generated/assets/mediaworks/textures/item/magic_cloak_default.png
hexdoc_mediaworks/_export/generated/assets/mediaworks/textures/item/magic_cloak_overlay.png
hexdoc_mediaworks/_export/generated/assets/mediaworks/textures/mob_effect/astral_projection.png
hexdoc_mediaworks/_export/generated/assets/mediaworks/textures/models/armor/magic_cloak.png
hexdoc_mediaworks/_export/generated/assets/mediaworks/textures/models/armor/magic_cloak_overlay.png
hexdoc_mediaworks/_export/generated/assets/minecraft/lang/en_us.json
hexdoc_mediaworks/_export/generated/assets/supplementaries/lang/en_us.json
hexdoc_mediaworks/_export/generated/assets/supplementaries/models/block/sack_closed.json
hexdoc_mediaworks/_export/generated/assets/supplementaries/models/item/sack.json
hexdoc_mediaworks/_export/generated/assets/supplementaries/textures/blocks/sack_bottom.png
hexdoc_mediaworks/_export/generated/assets/supplementaries/textures/blocks/sack_bottom1.png
hexdoc_mediaworks/_export/generated/assets/supplementaries/textures/blocks/sack_bottom2.png
hexdoc_mediaworks/_export/generated/assets/supplementaries/textures/blocks/sack_bottom_r.png
hexdoc_mediaworks-1.0.7.1.0.dev0.dist-info/METADATA
hexdoc_mediaworks-1.0.7.1.0.dev0.dist-info/WHEEL
hexdoc_mediaworks-1.0.7.1.0.dev0.dist-info/entry_points.txt
hexdoc_mediaworks-1.0.7.1.0.dev0.dist-info/licenses/LICENSE.md
hexdoc_mediaworks-1.0.7.1.0.dev0.dist-info/RECORD
