Metadata-Version: 2.3
Name: hexdoc-mediaworks
Version: 1.0.7.1.0.dev0
Summary: Python web book docgen and hexdoc plugin for Mediaworks.
Project-URL: Homepage, https://artynova.github.io/mediaworks/
Project-URL: Source, https://github.com/artynova/mediaworks
Author: artynova
License-File: LICENSE.md
Keywords: hexdoc
Requires-Python: >=3.11
Requires-Dist: hexdoc-hexcasting~=0.10.3.1.0.dev20
Provides-Extra: dev
Requires-Dist: ruff~=0.1.4; extra == 'dev'
